emfd/.gitignore
emfd/.ipynb_checkpoints/.gitignore-checkpoint
emfd/.ipynb_checkpoints/MANIFEST-checkpoint.in
emfd/.ipynb_checkpoints/__init__-checkpoint.py
emfd/.ipynb_checkpoints/emfd_scores-checkpoint.csv
emfd/.ipynb_checkpoints/load_mfds-checkpoint.py
emfd/.ipynb_checkpoints/main-checkpoint.py
emfd/.ipynb_checkpoints/mfd2_scores-checkpoint.csv
emfd/.ipynb_checkpoints/mfd_scores-checkpoint.csv
emfd/.ipynb_checkpoints/scoring-checkpoint.py
emfd/.ipynb_checkpoints/template_input-checkpoint.csv
emfd/.ipynb_checkpoints/test_out-checkpoint.csv
emfd/__init__.py
emfd/dictionaries/emfd_all_vice_virtue.pkl
emfd/dictionaries/emfd_scoring.csv
emfd/dictionaries/emfd_single_sent.pkl
emfd/dictionaries/emfd_single_vice_virtue.pkl
emfd/dictionaries/mfd2.0.dic
emfd/dictionaries/mft_original.dic
emfd/load_mfds.py
emfd/main.py
emfd/scoring.py
emfd/template_input.csv
emfd-0.1.0.dist-info/LICENSE
emfd-0.1.0.dist-info/METADATA
emfd-0.1.0.dist-info/WHEEL
emfd-0.1.0.dist-info/RECORD
