Metadata-Version: 2.1
Name: emfd
Version: 0.1.0
Summary: Extended Moral Foundation Dictionary Scoring
License: GPL3
Author: RakerZh
Author-email: gitrustz10@gmail.com
Requires-Python: >=3.12,<4.0
Classifier: License :: Other/Proprietary License
Classifier: Programming Language :: Python :: 3
Classifier: Programming Language :: Python :: 3.12
Requires-Dist: pandas (>=2.1.4,<3.0.0)
Requires-Dist: progressbar2 (>=4.3.2,<5.0.0)
Requires-Dist: scikit-learn (>=1.3.2,<2.0.0)
